LICENSE
README.md
setup.py
stbt_rig.py
stbt_rig.egg-info/PKG-INFO
stbt_rig.egg-info/SOURCES.txt
stbt_rig.egg-info/dependency_links.txt
stbt_rig.egg-info/entry_points.txt
stbt_rig.egg-info/requires.txt
stbt_rig.egg-info/top_level.txt