Metadata-Version: 2.1
Name: stbt-rig
Version: 33.0.0
Summary: Library for interacting with the Stb-tester Portal's REST API
Home-page: https://github.com/stb-tester/stbt-rig
Author: Stb-tester.com Ltd.
Author-email: support@stb-tester.com
Classifier: Development Status :: 5 - Production/Stable
Classifier: License :: OSI Approved :: MIT License
Classifier: Operating System :: OS Independent
Classifier: Programming Language :: Python :: 2.7
Classifier: Programming Language :: Python :: 3
Classifier: Topic :: Software Development :: Testing
Requires-Python: >=2.7
License-File: LICENSE
